{
    "overall_execution": {
        "start": "2025-06-23 23:40:06+00:00",
        "end": "2025-06-24 02:55:46+00:00"
    },
    "metadataframe_creation": {
        "start": "2025-06-23 23:40:06+00:00",
        "end": "2025-06-23 23:40:06+00:00"
    },
    "datafold_1_execution": {
        "start": "2025-06-23 23:40:18+00:00",
        "end": "2025-06-24 00:39:49+00:00"
    },
    "datafold_2_execution": {
        "start": "2025-06-24 00:39:50+00:00",
        "end": "2025-06-24 01:45:57+00:00"
    },
    "datafold_3_execution": {
        "start": "2025-06-24 01:45:59+00:00",
        "end": "2025-06-24 02:55:46+00:00"
    }
}